tsdiag/__init__.py
tsdiag/api.py
tsdiag/cli.py
tsdiag/core.py
tsdiag/fastapi_app.py
tsdiag/invertibility.py
tsdiag/stationarity.py
time_series_model_analysis_and_diagnostic_tool-0.1.2.dist-info/METADATA
time_series_model_analysis_and_diagnostic_tool-0.1.2.dist-info/WHEEL
time_series_model_analysis_and_diagnostic_tool-0.1.2.dist-info/entry_points.txt
time_series_model_analysis_and_diagnostic_tool-0.1.2.dist-info/licenses/LICENSE
time_series_model_analysis_and_diagnostic_tool-0.1.2.dist-info/RECORD
