Metadata-Version: 2.4
Name: time-series-model-analysis-and-diagnostic-tool
Version: 0.1.2
Summary: 时间序列模型分析与诊断工具 - 提供AR模型平稳性检验和MA模型可逆性检验功能
Project-URL: Homepage, https://github.com/zym9863/time-series-model-analysis-and-diagnostic-tool
Project-URL: Repository, https://github.com/zym9863/time-series-model-analysis-and-diagnostic-tool
Author-email: zym <ym214413520@gmail.com>
License-File: LICENSE
Keywords: analysis,diagnostic,invertibility,stationarity,time-series
Classifier: Development Status :: 4 - Beta
Classifier: Intended Audience :: Science/Research
Classifier: License :: OSI Approved :: MIT License
Classifier: Programming Language :: Python :: 3
Classifier: Programming Language :: Python :: 3.8
Classifier: Programming Language :: Python :: 3.9
Classifier: Programming Language :: Python :: 3.10
Classifier: Programming Language :: Python :: 3.11
Classifier: Programming Language :: Python :: 3.12
Classifier: Topic :: Scientific/Engineering :: Mathematics
Requires-Python: >=3.8
Requires-Dist: click>=8.0.0
Requires-Dist: fastapi>=0.100.0
Requires-Dist: numpy>=1.20.0
Requires-Dist: pydantic>=2.0.0
Requires-Dist: uvicorn[standard]>=0.22.0
